nbdev_test_ar/__init__.py
nbdev_test_ar/_modidx.py
nbdev_test_ar/core.py
nbdev_test_ar-0.0.1.dist-info/LICENSE
nbdev_test_ar-0.0.1.dist-info/METADATA
nbdev_test_ar-0.0.1.dist-info/WHEEL
nbdev_test_ar-0.0.1.dist-info/entry_points.txt
nbdev_test_ar-0.0.1.dist-info/top_level.txt
nbdev_test_ar-0.0.1.dist-info/RECORD
